nexus_test/__init__.py
nexus_test/main.py
nexus_test-0.0.1.dist-info/METADATA
nexus_test-0.0.1.dist-info/WHEEL
nexus_test-0.0.1.dist-info/top_level.txt
nexus_test-0.0.1.dist-info/RECORD
