Metadata-Version: 2.1
Name: nexus-test
Version: 0.0.1
Summary: test for Nexus
Home-page: UNKNOWN
Author: Marie-Lynne Block
Author-email: <marie-lynne.block@cm.be>
License: UNKNOWN
Keywords: python,test,nexus
Platform: UNKNOWN
Classifier: Development Status :: 1 - Planning
Classifier: Intended Audience :: Developers
Classifier: Programming Language :: Python :: 3
Classifier: Operating System :: Unix
Classifier: Operating System :: MacOS :: MacOS X
Classifier: Operating System :: Microsoft :: Windows
